<?xml version="1.0"?>
<PropertyList>
<path>VHHHcity4827.ac</path>
<model>
  <path>Models/Effects/pos_lamp_red_light_2st.xml</path>
  <offsets>
    <x-m>1629.74</x-m>
    <y-m>496.353</y-m>
    <z-m>-137.342</z-m>
    <pitch-deg> 0.00</pitch-deg>
    <heading-deg>0.0 </heading-deg>
  </offsets>
</model>
<model>
  <path>Models/Effects/pos_lamp_red_light_2st.xml</path>
  <offsets>
    <x-m>1628.22</x-m>
    <y-m>488.133</y-m>
    <z-m>-137.342</z-m>
    <pitch-deg> 0.00</pitch-deg>
    <heading-deg>0.0 </heading-deg>
  </offsets>
</model>
<model>
  <path>Models/Effects/pos_lamp_red_light_2st.xml</path>
  <offsets>
    <x-m>1636.77</x-m>
    <y-m>486.743</y-m>
    <z-m>-137.342</z-m>
    <pitch-deg> 0.00</pitch-deg>
    <heading-deg>0.0 </heading-deg>
  </offsets>
</model>
<model>
  <path>Models/Effects/pos_lamp_red_light_2st.xml</path>
  <offsets>
    <x-m>1638.28</x-m>
    <y-m>494.963</y-m>
    <z-m>-137.342</z-m>
    <pitch-deg> 0.00</pitch-deg>
    <heading-deg>0.0 </heading-deg>
  </offsets>
</model>
<model>
  <path>Models/Effects/pos_lamp_red_light_2st.xml</path>
  <offsets>
    <x-m>1402.13</x-m>
    <y-m>767.474</y-m>
    <z-m>-136.665</z-m>
    <pitch-deg> 0.00</pitch-deg>
    <heading-deg>0.0 </heading-deg>
  </offsets>
</model>
<model>
  <path>Models/Effects/pos_lamp_red_light_2st.xml</path>
  <offsets>
    <x-m>1412.1</x-m>
    <y-m>778.795</y-m>
    <z-m>-136.665</z-m>
    <pitch-deg> 0.00</pitch-deg>
    <heading-deg>0.0 </heading-deg>
  </offsets>
</model>
<model>
  <path>Models/Effects/pos_lamp_red_light_2st.xml</path>
  <offsets>
    <x-m>1415.98</x-m>
    <y-m>790.775</y-m>
    <z-m>-136.665</z-m>
    <pitch-deg> 0.00</pitch-deg>
    <heading-deg>0.0 </heading-deg>
  </offsets>
</model>
<model>
  <path>Models/Effects/pos_lamp_red_light_2st.xml</path>
  <offsets>
    <x-m>1406.36</x-m>
    <y-m>779.959</y-m>
    <z-m>-136.665</z-m>
    <pitch-deg> 0.00</pitch-deg>
    <heading-deg>0.0 </heading-deg>
  </offsets>
</model>
<model>
  <path>Models/Effects/pos_lamp_red_light_2st.xml</path>
  <offsets>
    <x-m>1377.07</x-m>
    <y-m>774.293</y-m>
    <z-m>-134.265</z-m>
    <pitch-deg> 0.00</pitch-deg>
    <heading-deg>0.0 </heading-deg>
  </offsets>
</model>
<model>
  <path>Models/Effects/pos_lamp_red_light_2st.xml</path>
  <offsets>
    <x-m>1380.66</x-m>
    <y-m>759.666</y-m>
    <z-m>-134.265</z-m>
    <pitch-deg> 0.00</pitch-deg>
    <heading-deg>0.0 </heading-deg>
  </offsets>
</model>
<model>
  <path>Models/Effects/pos_lamp_red_light_2st.xml</path>
  <offsets>
    <x-m>1394.45</x-m>
    <y-m>762.025</y-m>
    <z-m>-134.265</z-m>
    <pitch-deg> 0.00</pitch-deg>
    <heading-deg>0.0 </heading-deg>
  </offsets>
</model>
<model>
  <path>Models/Effects/pos_lamp_red_light_2st.xml</path>
  <offsets>
    <x-m>1391.68</x-m>
    <y-m>776.014</y-m>
    <z-m>-134.265</z-m>
    <pitch-deg> 0.00</pitch-deg>
    <heading-deg>0.0 </heading-deg>
  </offsets>
</model>
<model>
  <path>Models/Effects/pos_lamp_red_light_2st.xml</path>
  <offsets>
    <x-m>1232.18</x-m>
    <y-m>1685.49</y-m>
    <z-m>-146.336</z-m>
    <pitch-deg> 0.00</pitch-deg>
    <heading-deg>0.0 </heading-deg>
  </offsets>
</model>
<model>
  <path>Models/Effects/pos_lamp_red_light_2st.xml</path>
  <offsets>
    <x-m>1245.05</x-m>
    <y-m>1693.42</y-m>
    <z-m>-146.336</z-m>
    <pitch-deg> 0.00</pitch-deg>
    <heading-deg>0.0 </heading-deg>
  </offsets>
</model>
<model>
  <path>Models/Effects/pos_lamp_red_light_2st.xml</path>
  <offsets>
    <x-m>1250.9</x-m>
    <y-m>1710</y-m>
    <z-m>-146.336</z-m>
    <pitch-deg> 0.00</pitch-deg>
    <heading-deg>0.0 </heading-deg>
  </offsets>
</model>
<model>
  <path>Models/Effects/pos_lamp_red_light_2st.xml</path>
  <offsets>
    <x-m>1238.63</x-m>
    <y-m>1700.19</y-m>
    <z-m>-146.336</z-m>
    <pitch-deg> 0.00</pitch-deg>
    <heading-deg>0.0 </heading-deg>
  </offsets>
</model>
<model>
  <path>Models/Effects/pos_lamp_red_light_2st.xml</path>
  <offsets>
    <x-m>1032.97</x-m>
    <y-m>1839.17</y-m>
    <z-m>-162.924</z-m>
    <pitch-deg> 0.00</pitch-deg>
    <heading-deg>0.0 </heading-deg>
  </offsets>
</model>
<model>
  <path>Models/Effects/pos_lamp_red_light_2st.xml</path>
  <offsets>
    <x-m>1023.28</x-m>
    <y-m>1858.15</y-m>
    <z-m>-162.924</z-m>
    <pitch-deg> 0.00</pitch-deg>
    <heading-deg>0.0 </heading-deg>
  </offsets>
</model>
<model>
  <path>Models/Effects/pos_lamp_red_light_2st.xml</path>
  <offsets>
    <x-m>1005.47</x-m>
    <y-m>1846.48</y-m>
    <z-m>-162.924</z-m>
    <pitch-deg> 0.00</pitch-deg>
    <heading-deg>0.0 </heading-deg>
  </offsets>
</model>
<model>
  <path>Models/Effects/pos_lamp_red_light_2st.xml</path>
  <offsets>
    <x-m>1015.38</x-m>
    <y-m>1827.75</y-m>
    <z-m>-162.924</z-m>
    <pitch-deg> 0.00</pitch-deg>
    <heading-deg>0.0 </heading-deg>
  </offsets>
</model>
<model>
  <path>Models/Effects/pos_lamp_red_light_2st.xml</path>
  <offsets>
    <x-m>1614.75</x-m>
    <y-m>1338.82</y-m>
    <z-m>-117.728</z-m>
    <pitch-deg> 0.00</pitch-deg>
    <heading-deg>0.0 </heading-deg>
  </offsets>
</model>
<model>
  <path>Models/Effects/pos_lamp_red_light_2st.xml</path>
  <offsets>
    <x-m>1613.86</x-m>
    <y-m>1330.43</y-m>
    <z-m>-117.728</z-m>
    <pitch-deg> 0.00</pitch-deg>
    <heading-deg>0.0 </heading-deg>
  </offsets>
</model>
<model>
  <path>Models/Effects/pos_lamp_red_light_2st.xml</path>
  <offsets>
    <x-m>1621.9</x-m>
    <y-m>1329.83</y-m>
    <z-m>-117.728</z-m>
    <pitch-deg> 0.00</pitch-deg>
    <heading-deg>0.0 </heading-deg>
  </offsets>
</model>
<model>
  <path>Models/Effects/pos_lamp_red_light_2st.xml</path>
  <offsets>
    <x-m>1622.77</x-m>
    <y-m>1338.24</y-m>
    <z-m>-117.728</z-m>
    <pitch-deg> 0.00</pitch-deg>
    <heading-deg>0.0 </heading-deg>
  </offsets>
</model>
<model>
  <path>Models/Effects/pos_lamp_red_light_2st.xml</path>
  <offsets>
    <x-m>1552.29</x-m>
    <y-m>1394.3</y-m>
    <z-m>-119.179</z-m>
    <pitch-deg> 0.00</pitch-deg>
    <heading-deg>0.0 </heading-deg>
  </offsets>
</model>
<model>
  <path>Models/Effects/pos_lamp_red_light_2st.xml</path>
  <offsets>
    <x-m>1551.4</x-m>
    <y-m>1385.91</y-m>
    <z-m>-119.179</z-m>
    <pitch-deg> 0.00</pitch-deg>
    <heading-deg>0.0 </heading-deg>
  </offsets>
</model>
<model>
  <path>Models/Effects/pos_lamp_red_light_2st.xml</path>
  <offsets>
    <x-m>1559.44</x-m>
    <y-m>1385.31</y-m>
    <z-m>-119.179</z-m>
    <pitch-deg> 0.00</pitch-deg>
    <heading-deg>0.0 </heading-deg>
  </offsets>
</model>
<model>
  <path>Models/Effects/pos_lamp_red_light_2st.xml</path>
  <offsets>
    <x-m>1560.32</x-m>
    <y-m>1393.72</y-m>
    <z-m>-119.179</z-m>
    <pitch-deg> 0.00</pitch-deg>
    <heading-deg>0.0 </heading-deg>
  </offsets>
</model>
<model>
  <path>Models/Effects/pos_lamp_red_light_2st.xml</path>
  <offsets>
    <x-m>-222.592</x-m>
    <y-m>964.212</y-m>
    <z-m>-135.07</z-m>
    <pitch-deg> 0.00</pitch-deg>
    <heading-deg>0.0 </heading-deg>
  </offsets>
</model>
<model>
  <path>Models/Effects/pos_lamp_red_light_2st.xml</path>
  <offsets>
    <x-m>-261.449</x-m>
    <y-m>910.173</y-m>
    <z-m>-135.07</z-m>
    <pitch-deg> 0.00</pitch-deg>
    <heading-deg>0.0 </heading-deg>
  </offsets>
</model>
<model>
  <path>Models/Effects/pos_lamp_red_light_2st.xml</path>
  <offsets>
    <x-m>-231.24</x-m>
    <y-m>882.546</y-m>
    <z-m>-135.07</z-m>
    <pitch-deg> 0.00</pitch-deg>
    <heading-deg>0.0 </heading-deg>
  </offsets>
</model>
<model>
  <path>Models/Effects/pos_lamp_red_light_2st.xml</path>
  <offsets>
    <x-m>-191.342</x-m>
    <y-m>938.161</y-m>
    <z-m>-135.07</z-m>
    <pitch-deg> 0.00</pitch-deg>
    <heading-deg>0.0 </heading-deg>
  </offsets>
</model>
<model>
  <path>Models/Effects/pos_lamp_red_light_2st.xml</path>
  <offsets>
    <x-m>-263.918</x-m>
    <y-m>785.346</y-m>
    <z-m>-140.85</z-m>
    <pitch-deg> 0.00</pitch-deg>
    <heading-deg>0.0 </heading-deg>
  </offsets>
</model>
<model>
  <path>Models/Effects/pos_lamp_red_light_2st.xml</path>
  <offsets>
    <x-m>-336.162</x-m>
    <y-m>744.534</y-m>
    <z-m>-140.85</z-m>
    <pitch-deg> 0.00</pitch-deg>
    <heading-deg>0.0 </heading-deg>
  </offsets>
</model>
<model>
  <path>Models/Effects/pos_lamp_red_light_2st.xml</path>
  <offsets>
    <x-m>-272.943</x-m>
    <y-m>697.521</y-m>
    <z-m>-140.85</z-m>
    <pitch-deg> 0.00</pitch-deg>
    <heading-deg>0.0 </heading-deg>
  </offsets>
</model>
<model>
  <path>Models/Effects/pos_lamp_red_light_2st.xml</path>
  <offsets>
    <x-m>-225.161</x-m>
    <y-m>755.783</y-m>
    <z-m>-140.85</z-m>
    <pitch-deg> 0.00</pitch-deg>
    <heading-deg>0.0 </heading-deg>
  </offsets>
</model>
<model>
  <path>Models/Effects/pos_lamp_red_light_2st.xml</path>
  <offsets>
    <x-m>-201.353</x-m>
    <y-m>887.872</y-m>
    <z-m>-142.139</z-m>
    <pitch-deg> 0.00</pitch-deg>
    <heading-deg>0.0 </heading-deg>
  </offsets>
</model>
<model>
  <path>Models/Effects/pos_lamp_red_light_2st.xml</path>
  <offsets>
    <x-m>-148.499</x-m>
    <y-m>854.631</y-m>
    <z-m>-142.139</z-m>
    <pitch-deg> 0.00</pitch-deg>
    <heading-deg>0.0 </heading-deg>
  </offsets>
</model>
<model>
  <path>Models/Effects/pos_lamp_red_light_2st.xml</path>
  <offsets>
    <x-m>-124.713</x-m>
    <y-m>892.909</y-m>
    <z-m>-142.139</z-m>
    <pitch-deg> 0.00</pitch-deg>
    <heading-deg>0.0 </heading-deg>
  </offsets>
</model>
<model>
  <path>Models/Effects/pos_lamp_red_light_2st.xml</path>
  <offsets>
    <x-m>-177.567</x-m>
    <y-m>926.15</y-m>
    <z-m>-142.139</z-m>
    <pitch-deg> 0.00</pitch-deg>
    <heading-deg>0.0 </heading-deg>
  </offsets>
</model>
<model>
  <path>Models/Effects/pos_lamp_red_light_2st.xml</path>
  <offsets>
    <x-m>-26.5134</x-m>
    <y-m>968.786</y-m>
    <z-m>-73.6661</z-m>
    <pitch-deg> 0.00</pitch-deg>
    <heading-deg>0.0 </heading-deg>
  </offsets>
</model>
<model>
  <path>Models/Effects/pos_lamp_red_light_2st.xml</path>
  <offsets>
    <x-m>-15.3846</x-m>
    <y-m>962.955</y-m>
    <z-m>-73.6661</z-m>
    <pitch-deg> 0.00</pitch-deg>
    <heading-deg>0.0 </heading-deg>
  </offsets>
</model>
<model>
  <path>Models/Effects/pos_lamp_red_light_2st.xml</path>
  <offsets>
    <x-m>-7.48917</x-m>
    <y-m>969.538</y-m>
    <z-m>-73.6661</z-m>
    <pitch-deg> 0.00</pitch-deg>
    <heading-deg>0.0 </heading-deg>
  </offsets>
</model>
<model>
  <path>Models/Effects/pos_lamp_red_light_2st.xml</path>
  <offsets>
    <x-m>-36.1917</x-m>
    <y-m>977.14</y-m>
    <z-m>-73.6661</z-m>
    <pitch-deg> 0.00</pitch-deg>
    <heading-deg>0.0 </heading-deg>
  </offsets>
</model>
<model>
  <path>Models/Effects/pos_lamp_red_light_2st.xml</path>
  <offsets>
    <x-m>6.90637</x-m>
    <y-m>974.049</y-m>
    <z-m>-67.1238</z-m>
    <pitch-deg> 0.00</pitch-deg>
    <heading-deg>0.0 </heading-deg>
  </offsets>
</model>
<model>
  <path>Models/Effects/pos_lamp_red_light_2st.xml</path>
  <offsets>
    <x-m>18.9765</x-m>
    <y-m>970.599</y-m>
    <z-m>-67.1238</z-m>
    <pitch-deg> 0.00</pitch-deg>
    <heading-deg>0.0 </heading-deg>
  </offsets>
</model>
<model>
  <path>Models/Effects/pos_lamp_red_light_2st.xml</path>
  <offsets>
    <x-m>25.388</x-m>
    <y-m>978.644</y-m>
    <z-m>-67.1238</z-m>
    <pitch-deg> 0.00</pitch-deg>
    <heading-deg>0.0 </heading-deg>
  </offsets>
</model>
<model>
  <path>Models/Effects/pos_lamp_red_light_2st.xml</path>
  <offsets>
    <x-m>-4.24464</x-m>
    <y-m>980.271</y-m>
    <z-m>-67.1238</z-m>
    <pitch-deg> 0.00</pitch-deg>
    <heading-deg>0.0 </heading-deg>
  </offsets>
</model>
<model>
  <path>Models/Effects/pos_lamp_red_light_2st.xml</path>
  <offsets>
    <x-m>39.551</x-m>
    <y-m>985.648</y-m>
    <z-m>-64.2046</z-m>
    <pitch-deg> 0.00</pitch-deg>
    <heading-deg>0.0 </heading-deg>
  </offsets>
</model>
<model>
  <path>Models/Effects/pos_lamp_red_light_2st.xml</path>
  <offsets>
    <x-m>52.0641</x-m>
    <y-m>984.814</y-m>
    <z-m>-64.2046</z-m>
    <pitch-deg> 0.00</pitch-deg>
    <heading-deg>0.0 </heading-deg>
  </offsets>
</model>
<model>
  <path>Models/Effects/pos_lamp_red_light_2st.xml</path>
  <offsets>
    <x-m>56.6707</x-m>
    <y-m>994.044</y-m>
    <z-m>-64.2046</z-m>
    <pitch-deg> 0.00</pitch-deg>
    <heading-deg>0.0 </heading-deg>
  </offsets>
</model>
<model>
  <path>Models/Effects/pos_lamp_red_light_2st.xml</path>
  <offsets>
    <x-m>27.348</x-m>
    <y-m>989.388</y-m>
    <z-m>-64.2046</z-m>
    <pitch-deg> 0.00</pitch-deg>
    <heading-deg>0.0 </heading-deg>
  </offsets>
</model>
<model>
  <path>Models/Effects/pos_lamp_red_light_2st.xml</path>
  <offsets>
    <x-m>-111.425</x-m>
    <y-m>1388.48</y-m>
    <z-m>-192.782</z-m>
    <pitch-deg> 0.00</pitch-deg>
    <heading-deg>0.0 </heading-deg>
  </offsets>
</model>
<model>
  <path>Models/Effects/pos_lamp_red_light_2st.xml</path>
  <offsets>
    <x-m>-171.72</x-m>
    <y-m>1423.3</y-m>
    <z-m>-192.782</z-m>
    <pitch-deg> 0.00</pitch-deg>
    <heading-deg>0.0 </heading-deg>
  </offsets>
</model>
<model>
  <path>Models/Effects/pos_lamp_red_light_2st.xml</path>
  <offsets>
    <x-m>-192.704</x-m>
    <y-m>1386.52</y-m>
    <z-m>-192.782</z-m>
    <pitch-deg> 0.00</pitch-deg>
    <heading-deg>0.0 </heading-deg>
  </offsets>
</model>
<model>
  <path>Models/Effects/pos_lamp_red_light_2st.xml</path>
  <offsets>
    <x-m>-132.42</x-m>
    <y-m>1351.69</y-m>
    <z-m>-192.782</z-m>
    <pitch-deg> 0.00</pitch-deg>
    <heading-deg>0.0 </heading-deg>
  </offsets>
</model>
<model>
  <path>Models/Effects/pos_lamp_red_light_2st.xml</path>
  <offsets>
    <x-m>-160.082</x-m>
    <y-m>1818.26</y-m>
    <z-m>-106.496</z-m>
    <pitch-deg> 0.00</pitch-deg>
    <heading-deg>0.0 </heading-deg>
  </offsets>
</model>
<model>
  <path>Models/Effects/pos_lamp_red_light_2st.xml</path>
  <offsets>
    <x-m>-157.602</x-m>
    <y-m>1834.99</y-m>
    <z-m>-106.496</z-m>
    <pitch-deg> 0.00</pitch-deg>
    <heading-deg>0.0 </heading-deg>
  </offsets>
</model>
<model>
  <path>Models/Effects/pos_lamp_red_light_2st.xml</path>
  <offsets>
    <x-m>-177.024</x-m>
    <y-m>1841.44</y-m>
    <z-m>-106.496</z-m>
    <pitch-deg> 0.00</pitch-deg>
    <heading-deg>0.0 </heading-deg>
  </offsets>
</model>
<model>
  <path>Models/Effects/pos_lamp_red_light_2st.xml</path>
  <offsets>
    <x-m>-176.648</x-m>
    <y-m>1819.27</y-m>
    <z-m>-106.496</z-m>
    <pitch-deg> 0.00</pitch-deg>
    <heading-deg>0.0 </heading-deg>
  </offsets>
</model>
<model>
  <path>Models/Effects/pos_lamp_red_light_2st.xml</path>
  <offsets>
    <x-m>78.4412</x-m>
    <y-m>1776.73</y-m>
    <z-m>-110.791</z-m>
    <pitch-deg> 0.00</pitch-deg>
    <heading-deg>0.0 </heading-deg>
  </offsets>
</model>
<model>
  <path>Models/Effects/pos_lamp_red_light_2st.xml</path>
  <offsets>
    <x-m>70.0253</x-m>
    <y-m>1767.73</y-m>
    <z-m>-110.791</z-m>
    <pitch-deg> 0.00</pitch-deg>
    <heading-deg>0.0 </heading-deg>
  </offsets>
</model>
<model>
  <path>Models/Effects/pos_lamp_red_light_2st.xml</path>
  <offsets>
    <x-m>79.3935</x-m>
    <y-m>1754.43</y-m>
    <z-m>-110.791</z-m>
    <pitch-deg> 0.00</pitch-deg>
    <heading-deg>0.0 </heading-deg>
  </offsets>
</model>
<model>
  <path>Models/Effects/pos_lamp_red_light_2st.xml</path>
  <offsets>
    <x-m>84.7198</x-m>
    <y-m>1767.34</y-m>
    <z-m>-110.791</z-m>
    <pitch-deg> 0.00</pitch-deg>
    <heading-deg>0.0 </heading-deg>
  </offsets>
</model>
<model>
  <path>Models/Effects/pos_lamp_red_light_2st.xml</path>
  <offsets>
    <x-m>42.707</x-m>
    <y-m>1773.65</y-m>
    <z-m>-97.7684</z-m>
    <pitch-deg> 0.00</pitch-deg>
    <heading-deg>0.0 </heading-deg>
  </offsets>
</model>
<model>
  <path>Models/Effects/pos_lamp_red_light_2st.xml</path>
  <offsets>
    <x-m>62.6614</x-m>
    <y-m>1775.95</y-m>
    <z-m>-97.7684</z-m>
    <pitch-deg> 0.00</pitch-deg>
    <heading-deg>0.0 </heading-deg>
  </offsets>
</model>
<model>
  <path>Models/Effects/pos_lamp_red_light_2st.xml</path>
  <offsets>
    <x-m>58.232</x-m>
    <y-m>1789</y-m>
    <z-m>-97.7684</z-m>
    <pitch-deg> 0.00</pitch-deg>
    <heading-deg>0.0 </heading-deg>
  </offsets>
</model>
<model>
  <path>Models/Effects/pos_lamp_red_light_2st.xml</path>
  <offsets>
    <x-m>50.6245</x-m>
    <y-m>1783.96</y-m>
    <z-m>-97.7684</z-m>
    <pitch-deg> 0.00</pitch-deg>
    <heading-deg>0.0 </heading-deg>
  </offsets>
</model>
<model>
  <path>Models/Effects/pos_lamp_red_light_2st.xml</path>
  <offsets>
    <x-m>8.83316</x-m>
    <y-m>1782.92</y-m>
    <z-m>-118.219</z-m>
    <pitch-deg> 0.00</pitch-deg>
    <heading-deg>0.0 </heading-deg>
  </offsets>
</model>
<model>
  <path>Models/Effects/pos_lamp_red_light_2st.xml</path>
  <offsets>
    <x-m>25.1334</x-m>
    <y-m>1774.17</y-m>
    <z-m>-118.219</z-m>
    <pitch-deg> 0.00</pitch-deg>
    <heading-deg>0.0 </heading-deg>
  </offsets>
</model>
<model>
  <path>Models/Effects/pos_lamp_red_light_2st.xml</path>
  <offsets>
    <x-m>22.1214</x-m>
    <y-m>1789.54</y-m>
    <z-m>-118.219</z-m>
    <pitch-deg> 0.00</pitch-deg>
    <heading-deg>0.0 </heading-deg>
  </offsets>
</model>
<model>
  <path>Models/Effects/pos_lamp_red_light_2st.xml</path>
  <offsets>
    <x-m>16.2524</x-m>
    <y-m>1797.81</y-m>
    <z-m>-118.219</z-m>
    <pitch-deg> 0.00</pitch-deg>
    <heading-deg>0.0 </heading-deg>
  </offsets>
</model>
<model>
  <path>Models/Effects/pos_lamp_red_light_2st.xml</path>
  <offsets>
    <x-m>68.1539</x-m>
    <y-m>1003.55</y-m>
    <z-m>-61.2353</z-m>
    <pitch-deg> 0.00</pitch-deg>
    <heading-deg>0.0 </heading-deg>
  </offsets>
</model>
<model>
  <path>Models/Effects/pos_lamp_red_light_2st.xml</path>
  <offsets>
    <x-m>80.5784</x-m>
    <y-m>1005.35</y-m>
    <z-m>-61.2353</z-m>
    <pitch-deg> 0.00</pitch-deg>
    <heading-deg>0.0 </heading-deg>
  </offsets>
</model>
<model>
  <path>Models/Effects/pos_lamp_red_light_2st.xml</path>
  <offsets>
    <x-m>83.1696</x-m>
    <y-m>1015.34</y-m>
    <z-m>-61.2353</z-m>
    <pitch-deg> 0.00</pitch-deg>
    <heading-deg>0.0 </heading-deg>
  </offsets>
</model>
<model>
  <path>Models/Effects/pos_lamp_red_light_2st.xml</path>
  <offsets>
    <x-m>55.4526</x-m>
    <y-m>1004.66</y-m>
    <z-m>-61.2353</z-m>
    <pitch-deg> 0.00</pitch-deg>
    <heading-deg>0.0 </heading-deg>
  </offsets>
</model>
<model>
  <path>Models/Effects/pos_lamp_red_light_2st.xml</path>
  <offsets>
    <x-m>160.518</x-m>
    <y-m>1049.28</y-m>
    <z-m>-60.3386</z-m>
    <pitch-deg> 0.00</pitch-deg>
    <heading-deg>0.0 </heading-deg>
  </offsets>
</model>
<model>
  <path>Models/Effects/pos_lamp_red_light_2st.xml</path>
  <offsets>
    <x-m>172.987</x-m>
    <y-m>1053.58</y-m>
    <z-m>-60.3386</z-m>
    <pitch-deg> 0.00</pitch-deg>
    <heading-deg>0.0 </heading-deg>
  </offsets>
</model>
<model>
  <path>Models/Effects/pos_lamp_red_light_2st.xml</path>
  <offsets>
    <x-m>168.989</x-m>
    <y-m>1059.95</y-m>
    <z-m>-60.3386</z-m>
    <pitch-deg> 0.00</pitch-deg>
    <heading-deg>0.0 </heading-deg>
  </offsets>
</model>
<model>
  <path>Models/Effects/pos_lamp_red_light_2st.xml</path>
  <offsets>
    <x-m>155.845</x-m>
    <y-m>1054.98</y-m>
    <z-m>-60.3386</z-m>
    <pitch-deg> 0.00</pitch-deg>
    <heading-deg>0.0 </heading-deg>
  </offsets>
</model>
<model>
  <path>Models/Effects/pos_lamp_red_light_2st.xml</path>
  <offsets>
    <x-m>206.484</x-m>
    <y-m>1069.97</y-m>
    <z-m>-75.1519</z-m>
    <pitch-deg> 0.00</pitch-deg>
    <heading-deg>0.0 </heading-deg>
  </offsets>
</model>
<model>
  <path>Models/Effects/pos_lamp_red_light_2st.xml</path>
  <offsets>
    <x-m>218.953</x-m>
    <y-m>1074.27</y-m>
    <z-m>-75.1519</z-m>
    <pitch-deg> 0.00</pitch-deg>
    <heading-deg>0.0 </heading-deg>
  </offsets>
</model>
<model>
  <path>Models/Effects/pos_lamp_red_light_2st.xml</path>
  <offsets>
    <x-m>214.955</x-m>
    <y-m>1080.64</y-m>
    <z-m>-75.1519</z-m>
    <pitch-deg> 0.00</pitch-deg>
    <heading-deg>0.0 </heading-deg>
  </offsets>
</model>
<model>
  <path>Models/Effects/pos_lamp_red_light_2st.xml</path>
  <offsets>
    <x-m>201.811</x-m>
    <y-m>1075.67</y-m>
    <z-m>-75.1519</z-m>
    <pitch-deg> 0.00</pitch-deg>
    <heading-deg>0.0 </heading-deg>
  </offsets>
</model>
<model>
  <path>Models/Effects/pos_lamp_red_light_2st.xml</path>
  <offsets>
    <x-m>-330.68</x-m>
    <y-m>1217.3</y-m>
    <z-m>-168.472</z-m>
    <pitch-deg> 0.00</pitch-deg>
    <heading-deg>0.0 </heading-deg>
  </offsets>
</model>
<model>
  <path>Models/Effects/pos_lamp_red_light_2st.xml</path>
  <offsets>
    <x-m>-362.328</x-m>
    <y-m>1184.79</y-m>
    <z-m>-168.472</z-m>
    <pitch-deg> 0.00</pitch-deg>
    <heading-deg>0.0 </heading-deg>
  </offsets>
</model>
<model>
  <path>Models/Effects/pos_lamp_red_light_2st.xml</path>
  <offsets>
    <x-m>-335.663</x-m>
    <y-m>1158.51</y-m>
    <z-m>-168.472</z-m>
    <pitch-deg> 0.00</pitch-deg>
    <heading-deg>0.0 </heading-deg>
  </offsets>
</model>
<model>
  <path>Models/Effects/pos_lamp_red_light_2st.xml</path>
  <offsets>
    <x-m>-304.015</x-m>
    <y-m>1191.02</y-m>
    <z-m>-168.472</z-m>
    <pitch-deg> 0.00</pitch-deg>
    <heading-deg>0.0 </heading-deg>
  </offsets>
</model>
<model>
  <path>Models/Effects/pos_lamp_red_light_2st.xml</path>
  <offsets>
    <x-m>-535.75</x-m>
    <y-m>1023.48</y-m>
    <z-m>-148.995</z-m>
    <pitch-deg> 0.00</pitch-deg>
    <heading-deg>0.0 </heading-deg>
  </offsets>
</model>
<model>
  <path>Models/Effects/pos_lamp_red_light_2st.xml</path>
  <offsets>
    <x-m>-582.082</x-m>
    <y-m>1077.12</y-m>
    <z-m>-148.995</z-m>
    <pitch-deg> 0.00</pitch-deg>
    <heading-deg>0.0 </heading-deg>
  </offsets>
</model>
<model>
  <path>Models/Effects/pos_lamp_red_light_2st.xml</path>
  <offsets>
    <x-m>-612.789</x-m>
    <y-m>1050.28</y-m>
    <z-m>-148.995</z-m>
    <pitch-deg> 0.00</pitch-deg>
    <heading-deg>0.0 </heading-deg>
  </offsets>
</model>
<model>
  <path>Models/Effects/pos_lamp_red_light_2st.xml</path>
  <offsets>
    <x-m>-566.457</x-m>
    <y-m>996.629</y-m>
    <z-m>-148.995</z-m>
    <pitch-deg> 0.00</pitch-deg>
    <heading-deg>0.0 </heading-deg>
  </offsets>
</model>
<animation>
  <type>range</type>
  <min-m>0</min-m>
  <max-property>/sim/rendering/static-lod/bare</max-property>
  <object-name>LOD_bare</object-name>
</animation>

<animation>
  <type>range</type>
  <min-m>0</min-m>
  <max-property>/sim/rendering/static-lod/rough</max-property>
  <object-name>LOD_rough</object-name>
</animation>

<animation>
  <type>range</type>
  <min-m>0</min-m>
  <max-property>/sim/rendering/static-lod/detailed</max-property>
  <object-name>LOD_detail</object-name>
</animation>


</PropertyList>
